socks.py
sockshandler.py
pysocker-1.7.2.dist-info/licenses/LICENSE
pysocker-1.7.2.dist-info/METADATA
pysocker-1.7.2.dist-info/WHEEL
pysocker-1.7.2.dist-info/top_level.txt
pysocker-1.7.2.dist-info/RECORD
