Metadata-Version: 2.4
Name: PySocker
Version: 1.7.2
Summary: A Python SOCKS client module. See https://github.com/rickwoi/PythonSocks for more information.
Author-email: Anorov <anorov.vorona@gmail.com>
License: BSD-3-Clause
Project-URL: Homepage, https://github.com/rickwoi/PythonSocks
Project-URL: Repository, https://github.com/rickwoi/PythonSocks
Project-URL: Issues, https://github.com/rickwoi/PythonSocks/issues
Keywords: socks,proxy,socket,network
Classifier: Development Status :: 5 - Production/Stable
Classifier: Intended Audience :: Developers
Classifier: License :: OSI Approved :: BSD License
Classifier: Programming Language :: Python :: 3
Classifier: Programming Language :: Python :: 3.10
Classifier: Programming Language :: Python :: 3.11
Classifier: Programming Language :: Python :: 3.12
Classifier: Programming Language :: Python :: 3.13
Classifier: Programming Language :: Python :: 3 :: Only
Classifier: Topic :: Internet
Classifier: Topic :: Software Development :: Libraries :: Python Modules
Requires-Python: >=3.10
License-File: LICENSE
Provides-Extra: dev
Requires-Dist: pytest; extra == "dev"
Requires-Dist: pytest-cov; extra == "dev"
Requires-Dist: pytest-asyncio; extra == "dev"
Requires-Dist: mypy; extra == "dev"
Requires-Dist: tox; extra == "dev"
Dynamic: license-file
